nonebot_plugin_meme_stickers-0.2.8.dist-info/METADATA
nonebot_plugin_meme_stickers-0.2.8.dist-info/WHEEL
nonebot_plugin_meme_stickers-0.2.8.dist-info/entry_points.txt
nonebot_plugin_meme_stickers-0.2.8.dist-info/licenses/LICENSE
nonebot_plugin_meme_stickers/__init__.py
nonebot_plugin_meme_stickers/config.py
nonebot_plugin_meme_stickers/consts.py
nonebot_plugin_meme_stickers/draw/__init__.py
nonebot_plugin_meme_stickers/draw/grid.py
nonebot_plugin_meme_stickers/draw/pack_list.py
nonebot_plugin_meme_stickers/draw/sticker.py
nonebot_plugin_meme_stickers/draw/tools.py
nonebot_plugin_meme_stickers/handlers/__init__.py
nonebot_plugin_meme_stickers/handlers/generate.py
nonebot_plugin_meme_stickers/handlers/help.py
nonebot_plugin_meme_stickers/handlers/manage.py
nonebot_plugin_meme_stickers/handlers/shared.py
nonebot_plugin_meme_stickers/handlers/shortcut.py
nonebot_plugin_meme_stickers/scripts/__init__.py
nonebot_plugin_meme_stickers/scripts/gen_checksum.py
nonebot_plugin_meme_stickers/sticker_pack/__init__.py
nonebot_plugin_meme_stickers/sticker_pack/hub.py
nonebot_plugin_meme_stickers/sticker_pack/manager.py
nonebot_plugin_meme_stickers/sticker_pack/models.py
nonebot_plugin_meme_stickers/sticker_pack/pack.py
nonebot_plugin_meme_stickers/sticker_pack/update.py
nonebot_plugin_meme_stickers/utils/__init__.py
nonebot_plugin_meme_stickers/utils/file_source.py
nonebot_plugin_meme_stickers/utils/operation.py
nonebot_plugin_meme_stickers-0.2.8.dist-info/RECORD
