Metadata-Version: 2.1
Name: nonebot-plugin-meme-stickers
Version: 0.2.8
Summary: Make PJSK like meme stickers in one place
Author-Email: LgCookie <lgc2333@126.com>
License: MIT
Project-URL: homepage, https://github.com/lgc-NB2Dev/nonebot-plugin-meme-stickers
Requires-Python: <4.0,>=3.9
Requires-Dist: nonebot2>=2.4.1
Requires-Dist: nonebot-plugin-alconna>=0.55.1
Requires-Dist: nonebot-plugin-waiter>=0.8.1
Requires-Dist: nonebot-plugin-localstore>=0.7.4
Requires-Dist: skia-python>=134.0b12
Requires-Dist: cookit[loguru,nonebot-alconna,nonebot-localstore,pydantic]>=0.11.2
Requires-Dist: httpx>=0.27.2
Requires-Dist: tenacity>=9.0.0
